updateTechnews/__init__.py
CNNtech_News-0.1.4.dist-info/LICENSE
CNNtech_News-0.1.4.dist-info/METADATA
CNNtech_News-0.1.4.dist-info/WHEEL
CNNtech_News-0.1.4.dist-info/top_level.txt
CNNtech_News-0.1.4.dist-info/RECORD
