Metadata-Version: 2.1
Name: CNNtech-News
Version: 0.1.4
Summary: This package will provide you the most update of CNN Tech News
Home-page: https://github.com/ganirh0612/CNNtech_News
Author: Hasan Gani Rachmatullah
Author-email: ganirh0612@gmail.com
Project-URL: Bug Tracker, https://github.com/pypa/sampleproject/issues
Classifier: Programming Language :: Python :: 3
Classifier: Development Status :: 2 - Pre-Alpha
Classifier: License :: OSI Approved :: GNU General Public License v3 (GPLv3)
Classifier: Operating System :: OS Independent
License-File: LICENSE
